{
  "experiment_id": "736828d57dba4887",
  "timestamp": 1774780932.1885,
  "task_type": "T1",
  "fen": "3qkbnr/p5p1/2Qp3p/2n5/4PB2/2N5/PP3PPP/2KR3R b k - 0 15",
  "rule_names": [
    "bishop_as_rook"
  ],
  "model_moves": [
    "b7b5"
  ],
  "per_move_results": [
    {
      "legal": false,
      "is_old_rule": false,
      "uci_move": "b7b5",
      "is_inhibition_failure": false,
      "move_index": 0
    }
  ],
  "score": {
    "compliance_rate": 0.0,
    "inhibition_score": 1.0,
    "flexibility_index": 1.0,
    "composite_score": 0.5,
    "total_moves": 1,
    "legal_moves": 0,
    "inhibition_failures": 0
  },
  "metadata": {
    "model": "llama-3-70b",
    "raw_response": "b7b5",
    "difficulty_tier": "medium"
  }
}