{
  "experiment_id": "973327f3b838486c",
  "timestamp": 1776186079.1366506,
  "task_type": "T3",
  "fen": "r1b1k2r/pp4bp/nqn3p1/2ppPPN1/8/2P1B3/PP3Q1P/RN3RK1 b - - 0 16",
  "rule_names": [
    "knight_two_squares",
    "no_repeat_piece"
  ],
  "model_moves": [
    "d7d5",
    "b6c4",
    "c4b6"
  ],
  "per_move_results": [
    {
      "legal": false,
      "is_old_rule": false,
      "uci_move": "d7d5",
      "is_inhibition_failure": false,
      "move_index": 0
    },
    {
      "legal": false,
      "is_old_rule": false,
      "uci_move": "b6c4",
      "is_inhibition_failure": false,
      "move_index": 1
    },
    {
      "legal": false,
      "is_old_rule": false,
      "uci_move": "c4b6",
      "is_inhibition_failure": false,
      "move_index": 2
    }
  ],
  "score": {
    "compliance_rate": 0.0,
    "inhibition_score": 1.0,
    "flexibility_index": 1.0,
    "composite_score": 0.5,
    "total_moves": 3,
    "legal_moves": 0,
    "inhibition_failures": 0,
    "metacognition": null
  },
  "metadata": {
    "model": "llama-3-70b",
    "raw_response": "d7d5\nb6c4\nc4b6",
    "difficulty_tier": "hard"
  }
}